MANIFEST.in
README.rst
setup.py
django_senex_shop.egg-info/PKG-INFO
django_senex_shop.egg-info/SOURCES.txt
django_senex_shop.egg-info/dependency_links.txt
django_senex_shop.egg-info/not-zip-safe
django_senex_shop.egg-info/pbr.json
django_senex_shop.egg-info/requires.txt
django_senex_shop.egg-info/top_level.txt
senex_shop/__init__.py
senex_shop/admin.py
senex_shop/models.py
senex_shop/tests.py
senex_shop/urls.py
senex_shop/utils.py
senex_shop/views.py
senex_shop/cart/__init__.py
senex_shop/cart/admin.py
senex_shop/cart/managers.py
senex_shop/cart/middleware.py
senex_shop/cart/models.py
senex_shop/cart/urls.py
senex_shop/cart/views.py
senex_shop/cart/migrations/0001_initial.py
senex_shop/cart/migrations/__init__.py
senex_shop/cart/south_migrations/0001_initial.py
senex_shop/cart/south_migrations/0002_auto__add_field_cart_discount.py
senex_shop/cart/south_migrations/0003_auto__chg_field_cart_user.py
senex_shop/cart/south_migrations/__init__.py
senex_shop/checkout/__init__.py
senex_shop/checkout/admin.py
senex_shop/checkout/exceptions.py
senex_shop/checkout/forms.py
senex_shop/checkout/mixins.py
senex_shop/checkout/models.py
senex_shop/checkout/session.py
senex_shop/checkout/urls.py
senex_shop/checkout/utils.py
senex_shop/checkout/views.py
senex_shop/checkout/migrations/0001_initial.py
senex_shop/checkout/migrations/0002_auto_20150510_1101.py
senex_shop/checkout/migrations/__init__.py
senex_shop/checkout/south_migrations/0001_initial.py
senex_shop/checkout/south_migrations/0002_auto__chg_field_order_user__chg_field_userpaymentdetails_user.py
senex_shop/checkout/south_migrations/0003_auto__del_sale__add_stripecharge__add_field_order_charge.py
senex_shop/checkout/south_migrations/__init__.py
senex_shop/contact/__init__.py
senex_shop/contact/forms.py
senex_shop/contact/models.py
senex_shop/contact/utils.py
senex_shop/contact/migrations/0001_initial.py
senex_shop/contact/migrations/__init__.py
senex_shop/contact/south_migrations/0001_initial.py
senex_shop/contact/south_migrations/0002_auto__chg_field_useraddress_user.py
senex_shop/contact/south_migrations/__init__.py
senex_shop/core/__init__.py
senex_shop/core/admin.py
senex_shop/core/context_processors.py
senex_shop/core/models.py
senex_shop/core/tests.py
senex_shop/core/views.py
