Metadata-Version: 1.1
Name: django-senex-shop
Version: 0.3.1
Summary: Senex Shop
Home-page: http://www.github.com/endthestart/django-senex-shop
Author: Michael Anderson
Author-email: andermic@gmail.com
License: BSD
Keywords: django e-commerce online-shop
Platform: UNKNOWN
Classifier: Environment :: Web Environment
Classifier: Framework :: Django
Classifier: License :: OSI Approved :: BSD License
Classifier: Operating System :: OS Independent
Classifier: Programming Language :: Python
